thousandwords_core/__init__.py
thousandwords_core/resolver.py
thousandwords_core/serialize.py
thousandwords_core/serializer.py
thousandwords.core-0.7.0.dist-info/LICENSE
thousandwords.core-0.7.0.dist-info/WHEEL
thousandwords.core-0.7.0.dist-info/METADATA
thousandwords.core-0.7.0.dist-info/RECORD
