Metadata-Version: 2.1
Name: thousandwords.core
Version: 0.7.0
Summary: 
License: Proprietary
Author: Edouard Godfrey
Author-email: edouard@1000words-hq.com
Requires-Python: >=3.7.1,<4.0
Classifier: License :: Other/Proprietary License
Classifier: Programming Language :: Python :: 3
Classifier: Programming Language :: Python :: 3.10
Classifier: Programming Language :: Python :: 3.8
Classifier: Programming Language :: Python :: 3.9
Requires-Dist: cloudpickle (>=1.3.0)
